README.txt
setup.cfg
setup.py
Zenoss_Plugins.egg-info/PKG-INFO
Zenoss_Plugins.egg-info/SOURCES.txt
Zenoss_Plugins.egg-info/dependency_links.txt
Zenoss_Plugins.egg-info/top_level.txt
scripts/zenplugin.py
zenoss/__init__.py
zenoss/plugins/__init__.py
zenoss/plugins/darwin.py
zenoss/plugins/freebsd5.py
zenoss/plugins/linux2.py
