Metadata-Version: 1.0
Name: Zenoss-Plugins
Version: 1.0.0
Summary: Zenoss-Plugins collect information about your workstation and report them on the command line.
Home-page: http://www.zenoss.com
Author: Christopher Blunck
Author-email: chris@swcomplete.com
License: GPL
Keywords: network management
Platform: UNKNOWN
